<?xml version="1.0" encoding="UTF-8"?><laureate><id>117</id><firstname>Val Logsdon</firstname><surname>Fitch</surname><born>1923-03-10</born><died>0000-00-00</died><bornCountry>USA</bornCountry><bornCountryCode>US</bornCountryCode><bornCity>Merriman, NE</bornCity><gender>male</gender><year>1980</year><category>physics</category><share>2</share><motivation>"for the discovery of violations of fundamental symmetry principles in the decay of neutral K-mesons"</motivation><name>Princeton University</name><city>Princeton, NJ</city><country>USA</country></laureate>