<?xml version="1.0" encoding="UTF-8"?><laureate><id>193</id><firstname>Frédéric</firstname><surname>Joliot</surname><born>1900-03-19</born><died>1958-08-14</died><bornCountry>France</bornCountry><bornCountryCode>FR</bornCountryCode><bornCity>Paris</bornCity><diedCountry>France</diedCountry><diedCountryCode>FR</diedCountryCode><diedCity>Paris</diedCity><gender>male</gender><year>1935</year><category>chemistry</category><share>2</share><motivation>"in recognition of their synthesis of new radioactive elements"</motivation><name>Institut du Radium</name><city>Paris</city><country>France</country></laureate>