<?xml version="1.0" encoding="UTF-8"?><laureate><id>324</id><firstname>Edgar Douglas</firstname><surname>Adrian</surname><born>1889-11-30</born><died>1977-08-08</died><bornCountry>United Kingdom</bornCountry><bornCountryCode>GB</bornCountryCode><bornCity>London</bornCity><diedCountry>United Kingdom</diedCountry><diedCountryCode>GB</diedCountryCode><diedCity>Cambridge</diedCity><gender>male</gender><year>1932</year><category>medicine</category><share>2</share><motivation>"for their discoveries regarding the functions of neurons"</motivation><name>University of Cambridge</name><city>Cambridge</city><country>United Kingdom</country></laureate>