<?xml version="1.0" encoding="UTF-8"?><laureate><id>50</id><firstname>Wolfgang</firstname><surname>Pauli</surname><born>1900-04-25</born><died>1958-12-15</died><bornCountry>Austria</bornCountry><bornCountryCode>AT</bornCountryCode><bornCity>Vienna</bornCity><diedCountry>Switzerland</diedCountry><diedCountryCode>CH</diedCountryCode><diedCity>Zurich</diedCity><gender>male</gender><year>1945</year><category>physics</category><share>1</share><motivation>"for the discovery of the Exclusion Principle, also called the Pauli Principle"</motivation><name>Princeton University</name><city>Princeton, NJ</city><country>USA</country></laureate>