<?xml version="1.0" encoding="UTF-8"?><laureate><id>556</id><firstname>Frederik Willem</firstname><surname>de Klerk</surname><born>1936-03-18</born><died>0000-00-00</died><bornCountry>South Africa</bornCountry><bornCountryCode>ZA</bornCountryCode><bornCity>Johannesburg</bornCity><gender>male</gender><year>1993</year><category>peace</category><share>2</share><motivation>"for their work for the peaceful termination of the apartheid regime, and for laying the foundations for a new democratic South Africa"</motivation></laureate>