<?xml version="1.0" encoding="UTF-8"?><laureate><id>593</id><firstname>William Butler</firstname><surname>Yeats</surname><born>1865-06-13</born><died>1939-01-28</died><bornCountry>Ireland</bornCountry><bornCountryCode>IE</bornCountryCode><bornCity>Dublin</bornCity><diedCountry>France</diedCountry><diedCountryCode>FR</diedCountryCode><diedCity>Roquebrune-Cap-Martin</diedCity><gender>male</gender><year>1923</year><category>literature</category><share>1</share><motivation>"for his always inspired poetry, which in a highly artistic form gives expression to the spirit of a whole nation"</motivation></laureate>