<?xml version="1.0" encoding="UTF-8"?><laureate><id>670</id><firstname>Toni</firstname><surname>Morrison</surname><born>1931-02-18</born><died>0000-00-00</died><bornCountry>USA</bornCountry><bornCountryCode>US</bornCountryCode><bornCity>Lorain, OH</bornCity><gender>female</gender><year>1993</year><category>literature</category><share>1</share><motivation>"who in novels characterized by visionary force and poetic import, gives life to an essential aspect of American reality"</motivation></laureate>