<?xml version="1.0" encoding="UTF-8"?><laureate><id>701</id><firstname>Robert M.</firstname><surname>Solow</surname><born>1924-08-23</born><died>0000-00-00</died><bornCountry>USA</bornCountry><bornCountryCode>US</bornCountryCode><bornCity>Brooklyn, NY</bornCity><gender>male</gender><year>1987</year><category>economics</category><share>1</share><motivation>"for his contributions to the theory of economic growth"</motivation><name>Massachusetts Institute of Technology (MIT)</name><city>Cambridge, MA</city><country>USA</country></laureate>