<?xml version="1.0" encoding="UTF-8"?><laureate><id>8</id><firstname>Lord Rayleigh</firstname><surname>(John William Strutt)</surname><born>1842-11-12</born><died>1919-06-30</died><bornCountry>United Kingdom</bornCountry><bornCountryCode>GB</bornCountryCode><bornCity>Langford Grove, Maldon, Essex</bornCity><diedCountry>United Kingdom</diedCountry><diedCountryCode>GB</diedCountryCode><gender>male</gender><year>1904</year><category>physics</category><share>1</share><motivation>"for his investigations of the densities of the most important gases and for his discovery of argon in connection with these studies"</motivation><name>Royal Institution of Great Britain</name><city>London</city><country>United Kingdom</country></laureate>